setup.py
appomatic_migratedata/__app__.py
appomatic_migratedata/__init__.py
appomatic_migratedata.egg-info/PKG-INFO
appomatic_migratedata.egg-info/SOURCES.txt
appomatic_migratedata.egg-info/dependency_links.txt
appomatic_migratedata.egg-info/requires.txt
appomatic_migratedata.egg-info/top_level.txt
appomatic_migratedata/management/__init__.py
appomatic_migratedata/management/commands/__init__.py
appomatic_migratedata/management/commands/migratedata.py