Metadata-Version: 1.0
Name: appomatic-migratedata
Version: 0.0.1
Summary: Shortcut for dumpdata + loaddata to migrate larger datasets between two live databases.
Home-page: http://github.com/redhog/appomatic_migratedata
Author: RedHog (Egil Moeller)
Author-email: egil@skytruth.org
License: BSD
Keywords: appomatic django database dump restore migrate
Platform: UNKNOWN
